pmg_lammps/__init__.py
pmg_lammps/__main__.py
pmg_lammps/analysis.py
pmg_lammps/calculator.py
pmg_lammps/core.py
pmg_lammps/inputs.py
pmg_lammps/logging.py
pmg_lammps/output.py
pmg_lammps/sets.py
pmg_lammps/utils.py
pmg_lammps/calculator/__init__.py
pmg_lammps/calculator/__main__.py
pmg_lammps/calculator/client.py
pmg_lammps/calculator/process.py
pmg_lammps/calculator/scheduler.py
pmg_lammps/calculator/worker.py
pmg_lammps/cli/__init__.py
pmg_lammps/cli/benchmark.py
pmg_lammps/cli/calculator.py
pmg_lammps/sets/neb.json
pmg_lammps/sets/nve.json
pmg_lammps/sets/relax.json
pmg_lammps/sets/static.json
pymatgen_lammps-0.4.5.dist-info/METADATA
pymatgen_lammps-0.4.5.dist-info/RECORD
pymatgen_lammps-0.4.5.dist-info/WHEEL
pymatgen_lammps-0.4.5.dist-info/entry_points.txt
pymatgen_lammps-0.4.5.dist-info/top_level.txt
