Metadata-Version: 2.1
Name: pymatgen-lammps
Version: 0.4.5
Summary: A LAMMPS wrapper using pymatgen
Home-page: https://gitlab.com/costrouc/pymatgen-lammps
Author: Chris Ostrouchov
Author-email: chris.ostrouchov+pymatgen-lammps@gmail.com
License: UNKNOWN
Download-URL: https://gitlab.com/costrouc/pymatgen-lammps/repository/archive.zip?ref=v0.4.5
Keywords: lammps pymatgen wrapper
Platform: UNKNOWN
Classifier: License :: OSI Approved :: MIT License
Classifier: Programming Language :: Python
Classifier: Programming Language :: Python :: 3.6
Provides-Extra: zmq_legos
Requires-Dist: pymatgen
Provides-Extra: zmq_legos
Requires-Dist: zmq-legos; extra == 'zmq_legos'
